elbowK/__init__.py
elbowK/elbow.py
elbowk-1.0.dist-info/licenses/LICENSE
elbowk-1.0.dist-info/METADATA
elbowk-1.0.dist-info/WHEEL
elbowk-1.0.dist-info/top_level.txt
elbowk-1.0.dist-info/RECORD
